sqshield/__init__.py
sqshield/cli.py
sqshield/predict.py
sqshield/model/sql_injection_model.pkl
sqshield-0.1.2.dist-info/METADATA
sqshield-0.1.2.dist-info/WHEEL
sqshield-0.1.2.dist-info/entry_points.txt
sqshield-0.1.2.dist-info/top_level.txt
sqshield-0.1.2.dist-info/RECORD
