Metadata-Version: 2.4
Name: sqshield
Version: 0.1.2
Summary: CLI tool for Detecting SQL Injections
Author-email: Pranav Dhumale <pranavdhumale2812@gmail.com>
Requires-Python: >=3.8
Requires-Dist: click
Requires-Dist: joblib
Requires-Dist: pandas
Requires-Dist: lightgbm
Requires-Dist: scikit-learn
